LICENSE
MANIFEST.in
README.md
setup.py
tox.ini
clea/__init__.py
clea/__main__.py
clea/cache.py
clea/core.py
clea/join.py
clea/misc.py
clea/regexes.py
clea/server.py
clea/templates/upload.html
scielo_clea.egg-info/PKG-INFO
scielo_clea.egg-info/SOURCES.txt
scielo_clea.egg-info/dependency_links.txt
scielo_clea.egg-info/entry_points.txt
scielo_clea.egg-info/requires.txt
scielo_clea.egg-info/top_level.txt
tests/test_cli.py
tests/json/broken_article.json
tests/json/empty.json
tests/xml/Vkbh7CKQDNQzX7bW3cQVdJx.xml
tests/xml/broken_article.xml
tests/xml/empty.xml