Metadata-Version: 2.1
Name: scielo-clea
Version: 0.4.4
Summary: SciELO Publishing Schema XML document front matter metadata reader/sanitizer
Home-page: https://github.com/scieloorg/clea
Author: Danilo de Jesus da Silva Bellini
Author-email: danilo.bellini@gmail.com
License: 2-clause BSD
Platform: UNKNOWN
Classifier: Development Status :: 2 - Pre-Alpha
Classifier: Environment :: Other Environment
Classifier: Environment :: Web Environment
Classifier: Framework :: Flask
Classifier: Intended Audience :: Science/Research
Classifier: License :: OSI Approved :: BSD License
Classifier: Programming Language :: Python :: 3
Classifier: Programming Language :: Python :: 3.6
Classifier: Programming Language :: Python :: 3.7
Classifier: Programming Language :: Python :: 3 :: Only
Classifier: Topic :: Scientific/Engineering :: Information Analysis
Classifier: Topic :: Text Processing
Classifier: Topic :: Text Processing :: Markup
Classifier: Topic :: Text Processing :: Markup :: XML
Classifier: Operating System :: OS Independent
Requires-Python: >=3.6
Provides-Extra: cli
Provides-Extra: server
Provides-Extra: all
